misc/ri_fa.v
module ri_fa (
    input clk,
    input signal,
    output reg rise,
    output reg fall
);
    
    reg prev_signal;

    always @( posedge clk) begin
        rise <= (signal & ~prev_signal);
        fall <= (~signal & prev_signal);
        prev_signal <= signal;
    end

endmodule

misc/tb_ri_fa.v
`default_nettype none

module tb_ri_fa;
reg clk;
reg signal;
wire rise;
wire fall;

ri_fa uut
(
    .clk (clk),
    .signal(signal),
    .rise(rise),
    .fall(fall)

);

localparam CLK_PERIOD = 10;
always #(CLK_PERIOD/2) clk=~clk;

initial begin
    $dumpfile("tb_ri_fa.vcd");
    $dumpvars(0, tb_ri_fa);
end

initial begin
   // Initialize signals
        clk = 0;
        signal = 0;
        
        // Test rising edge
        #10 signal = 1;  // Rising edge at time = 10ns
        #10 signal = 1;  // Hold high

        // Test falling edge
        #10 signal = 0;  // Falling edge at time = 30ns
        #10 signal = 0;  // Hold low

        // Another rising edge
        #10 signal = 1;  // Rising edge at time = 50ns
        #10 signal = 1;  // Hold high

        // Another falling edge
        #10 signal = 0;  // Falling edge at time = 70ns
        #10 signal = 0;  // Hold low

        // End simulation
        #20 $finish;
end

endmodule
`default_nettype wire

misc/tb_ri_fa.vcd
$date
	Tue Nov 12 04:19:36 2024
$end
$version
	Icarus Verilog
$end
$timescale
	1s
$end
$scope module tb_ri_fa $end
$var wire 1 ! rise $end
$var wire 1 " fall $end
$var parameter 32 # CLK_PERIOD $end
$var reg 1 $ clk $end
$var reg 1 % signal $end
$scope module uut $end
$var wire 1 $ clk $end
$var wire 1 % signal $end
$var reg 1 " fall $end
$var reg 1 & prev_signal $end
$var reg 1 ! rise $end
$upscope $end
$upscope $end
$enddefinitions $end
$comment Show the parameter values. $end
$dumpall
b1010 #
$end
#0
$dumpvars
x&
0%
0$
x"
x!
$end
#5
0&
0!
1$
#10
0$
1%
#15
1&
0"
1!
1$
#20
0$
#25
0!
1$
#30
0$
0%
#35
0&
1"
1$
#40
0$
#45
0"
1$
#50
0$
1%
#55
1&
1!
1$
#60
0$
#65
0!
1$
#70
0$
0%
#75
0&
1"
1$
#80
0$
#85
0"
1$
