clk_dic-odd/clkby15.v
module clkby15 (
    input clk,
    input rst,
    output clk_out
);

    reg [3:0] posc, negc;

always @ (posedge clk) begin
    if (rst) begin
        posc <= 4'b0000;
    end
    else if (posc == 4'b1110) begin
        posc <= 4'b0000;
    end
    else begin
        posc <= posc + 1; 
    end
end

always @ (negedge clk) begin
    if (rst) begin
        negc <= 4'b0000;
    end
    else if (negc == 4'b1110) begin
        negc <= 4'b0000;
    end
    else begin
        negc <= negc + 1; 
    end
end

assign clk_out = (( posc > 7)| (negc > 7));

endmodule

clk_dic-odd/tb_clkby15.v
module tb_clkby15;

reg clk;
reg rst;
wire clk_out;

clkby15 m1 (

    .clk(clk),
    .rst(rst),
    .clk_out(clk_out)
);

initial
    clk= 1'b0;
always
    #5  clk=~clk; 
initial begin
    #5 rst=1'b1;
    #10 rst=1'b0;
    #1000 $finish;
end
 
initial
    $monitor("clk=%b,reset=%b,clk_out=%b",clk,rst,clk_out);
 
initial begin
    $dumpfile("tb_clkby15.vcd");
    $dumpvars(0,tb_clkby15);
end 


endmodule

clk_dic-odd/tb_clkby15.vcd
$date
	Sat Nov 16 21:57:48 2024
$end
$version
	Icarus Verilog
$end
$timescale
	1s
$end
$scope module tb_clkby15 $end
$var wire 1 ! clk_out $end
$var reg 1 " clk $end
$var reg 1 # rst $end
$scope module m1 $end
$var wire 1 " clk $end
$var wire 1 ! clk_out $end
$var wire 1 # rst $end
$var reg 4 $ negc [3:0] $end
$var reg 4 % posc [3:0] $end
$upscope $end
$upscope $end
$enddefinitions $end
$comment Show the parameter values. $end
$dumpall
$end
#0
$dumpvars
bx %
bx $
x#
0"
x!
$end
#5
b0 %
1#
1"
#10
0!
b0 $
0"
#15
b1 %
1"
0#
#20
b1 $
0"
#25
b10 %
1"
#30
b10 $
0"
#35
b11 %
1"
#40
b11 $
0"
#45
b100 %
1"
#50
b100 $
0"
#55
b101 %
1"
#60
b101 $
0"
#65
b110 %
1"
#70
b110 $
0"
#75
b111 %
1"
#80
b111 $
0"
#85
1!
b1000 %
1"
#90
b1000 $
0"
#95
b1001 %
1"
#100
b1001 $
0"
#105
b1010 %
1"
#110
b1010 $
0"
#115
b1011 %
1"
#120
b1011 $
0"
#125
b1100 %
1"
#130
b1100 $
0"
#135
b1101 %
1"
#140
b1101 $
0"
#145
b1110 %
1"
#150
b1110 $
0"
#155
b0 %
1"
#160
0!
b0 $
0"
#165
b1 %
1"
#170
b1 $
0"
#175
b10 %
1"
#180
b10 $
0"
#185
b11 %
1"
#190
b11 $
0"
#195
b100 %
1"
#200
b100 $
0"
#205
b101 %
1"
#210
b101 $
0"
#215
b110 %
1"
#220
b110 $
0"
#225
b111 %
1"
#230
b111 $
0"
#235
1!
b1000 %
1"
#240
b1000 $
0"
#245
b1001 %
1"
#250
b1001 $
0"
#255
b1010 %
1"
#260
b1010 $
0"
#265
b1011 %
1"
#270
b1011 $
0"
#275
b1100 %
1"
#280
b1100 $
0"
#285
b1101 %
1"
#290
b1101 $
0"
#295
b1110 %
1"
#300
b1110 $
0"
#305
b0 %
1"
#310
0!
b0 $
0"
#315
b1 %
1"
#320
b1 $
0"
#325
b10 %
1"
#330
b10 $
0"
#335
b11 %
1"
#340
b11 $
0"
#345
b100 %
1"
#350
b100 $
0"
#355
b101 %
1"
#360
b101 $
0"
#365
b110 %
1"
#370
b110 $
0"
#375
b111 %
1"
#380
b111 $
0"
#385
1!
b1000 %
1"
#390
b1000 $
0"
#395
b1001 %
1"
#400
b1001 $
0"
#405
b1010 %
1"
#410
b1010 $
0"
#415
b1011 %
1"
#420
b1011 $
0"
#425
b1100 %
1"
#430
b1100 $
0"
#435
b1101 %
1"
#440
b1101 $
0"
#445
b1110 %
1"
#450
b1110 $
0"
#455
b0 %
1"
#460
0!
b0 $
0"
#465
b1 %
1"
#470
b1 $
0"
#475
b10 %
1"
#480
b10 $
0"
#485
b11 %
1"
#490
b11 $
0"
#495
b100 %
1"
#500
b100 $
0"
#505
b101 %
1"
#510
b101 $
0"
#515
b110 %
1"
#520
b110 $
0"
#525
b111 %
1"
#530
b111 $
0"
#535
1!
b1000 %
1"
#540
b1000 $
0"
#545
b1001 %
1"
#550
b1001 $
0"
#555
b1010 %
1"
#560
b1010 $
0"
#565
b1011 %
1"
#570
b1011 $
0"
#575
b1100 %
1"
#580
b1100 $
0"
#585
b1101 %
1"
#590
b1101 $
0"
#595
b1110 %
1"
#600
b1110 $
0"
#605
b0 %
1"
#610
0!
b0 $
0"
#615
b1 %
1"
#620
b1 $
0"
#625
b10 %
1"
#630
b10 $
0"
#635
b11 %
1"
#640
b11 $
0"
#645
b100 %
1"
#650
b100 $
0"
#655
b101 %
1"
#660
b101 $
0"
#665
b110 %
1"
#670
b110 $
0"
#675
b111 %
1"
#680
b111 $
0"
#685
1!
b1000 %
1"
#690
b1000 $
0"
#695
b1001 %
1"
#700
b1001 $
0"
#705
b1010 %
1"
#710
b1010 $
0"
#715
b1011 %
1"
#720
b1011 $
0"
#725
b1100 %
1"
#730
b1100 $
0"
#735
b1101 %
1"
#740
b1101 $
0"
#745
b1110 %
1"
#750
b1110 $
0"
#755
b0 %
1"
#760
0!
b0 $
0"
#765
b1 %
1"
#770
b1 $
0"
#775
b10 %
1"
#780
b10 $
0"
#785
b11 %
1"
#790
b11 $
0"
#795
b100 %
1"
#800
b100 $
0"
#805
b101 %
1"
#810
b101 $
0"
#815
b110 %
1"
#820
b110 $
0"
#825
b111 %
1"
#830
b111 $
0"
#835
1!
b1000 %
1"
#840
b1000 $
0"
#845
b1001 %
1"
#850
b1001 $
0"
#855
b1010 %
1"
#860
b1010 $
0"
#865
b1011 %
1"
#870
b1011 $
0"
#875
b1100 %
1"
#880
b1100 $
0"
#885
b1101 %
1"
#890
b1101 $
0"
#895
b1110 %
1"
#900
b1110 $
0"
#905
b0 %
1"
#910
0!
b0 $
0"
#915
b1 %
1"
#920
b1 $
0"
#925
b10 %
1"
#930
b10 $
0"
#935
b11 %
1"
#940
b11 $
0"
#945
b100 %
1"
#950
b100 $
0"
#955
b101 %
1"
#960
b101 $
0"
#965
b110 %
1"
#970
b110 $
0"
#975
b111 %
1"
#980
b111 $
0"
#985
1!
b1000 %
1"
#990
b1000 $
0"
#995
b1001 %
1"
#1000
b1001 $
0"
#1005
b1010 %
1"
#1010
b1010 $
0"
#1015
b1011 %
1"
