clk4nf/clk4nf.v
module clkby15 (
    input clk,
    input rst,
    output clk_out
);

    reg [2:0] posc, negc;

always @ (posedge clk) begin
    if (rst) begin
        posc <= 3'b000;
    end
    else if (posc == 3'b100) begin
        posc <= 3'b000;
    end
    else begin
        posc <= posc + 1; 
    end
end

always @ (negedge clk) begin
    if (rst) begin
        negc <= 3'b000;
    end
    else if (negc == 3'b100) begin
        negc <= 3'b000;
    end
    else begin
        negc <= negc + 1; 
    end
end

assign clk_out = 

endmodule

clk4nf/tb_clk4nf.v
module tb_clk4nf;

reg clk;
reg rst;
wire clk_out;

clkby15 m1 (

    .clk(clk),
    .rst(rst),
    .clk_out(clk_out)
);

initial
    clk= 1'b0;
always
    #5  clk=~clk; 
initial begin
    #5 rst=1'b1;
    #10 rst=1'b0;
    #1000 $finish;
end
 
initial
    $monitor("clk=%b,reset=%b,clk_out=%b",clk,rst,clk_out);
 
initial begin
    $dumpfile("tb_clk4nf.vcd");
    $dumpvars(0,tb_clk4nf);
end 


endmodule

clk4nf/tb_clk4nf.vcd
$date
	Sat Nov 16 22:26:28 2024
$end
$version
	Icarus Verilog
$end
$timescale
	1s
$end
$scope module tb_clk4nf $end
$var wire 1 ! clk_out $end
$var reg 1 " clk $end
$var reg 1 # rst $end
$scope module m1 $end
$var wire 1 " clk $end
$var wire 1 ! clk_out $end
$var wire 1 # rst $end
$var reg 3 $ negc [2:0] $end
$var reg 3 % posc [2:0] $end
$upscope $end
$upscope $end
$enddefinitions $end
$comment Show the parameter values. $end
$dumpall
$end
#0
$dumpvars
bx %
bx $
x#
0"
x!
$end
#5
b0 %
1#
1"
#10
1!
b0 $
0"
#15
b1 %
1"
0#
#20
b1 $
0"
#25
b10 %
1"
#30
b10 $
0"
#35
b11 %
1"
#40
b11 $
0"
#45
b100 %
1"
#50
b100 $
0"
#55
0!
b0 %
1"
#60
1!
b0 $
0"
#65
b1 %
1"
#70
b1 $
0"
#75
b10 %
1"
#80
b10 $
0"
#85
b11 %
1"
#90
b11 $
0"
#95
b100 %
1"
#100
b100 $
0"
#105
0!
b0 %
1"
#110
1!
b0 $
0"
#115
b1 %
1"
#120
b1 $
0"
#125
b10 %
1"
#130
b10 $
0"
#135
b11 %
1"
#140
b11 $
0"
#145
b100 %
1"
#150
b100 $
0"
#155
0!
b0 %
1"
#160
1!
b0 $
0"
#165
b1 %
1"
#170
b1 $
0"
#175
b10 %
1"
#180
b10 $
0"
#185
b11 %
1"
#190
b11 $
0"
#195
b100 %
1"
#200
b100 $
0"
#205
0!
b0 %
1"
#210
1!
b0 $
0"
#215
b1 %
1"
#220
b1 $
0"
#225
b10 %
1"
#230
b10 $
0"
#235
b11 %
1"
#240
b11 $
0"
#245
b100 %
1"
#250
b100 $
0"
#255
0!
b0 %
1"
#260
1!
b0 $
0"
#265
b1 %
1"
#270
b1 $
0"
#275
b10 %
1"
#280
b10 $
0"
#285
b11 %
1"
#290
b11 $
0"
#295
b100 %
1"
#300
b100 $
0"
#305
0!
b0 %
1"
#310
1!
b0 $
0"
#315
b1 %
1"
#320
b1 $
0"
#325
b10 %
1"
#330
b10 $
0"
#335
b11 %
1"
#340
b11 $
0"
#345
b100 %
1"
#350
b100 $
0"
#355
0!
b0 %
1"
#360
1!
b0 $
0"
#365
b1 %
1"
#370
b1 $
0"
#375
b10 %
1"
#380
b10 $
0"
#385
b11 %
1"
#390
b11 $
0"
#395
b100 %
1"
#400
b100 $
0"
#405
0!
b0 %
1"
#410
1!
b0 $
0"
#415
b1 %
1"
#420
b1 $
0"
#425
b10 %
1"
#430
b10 $
0"
#435
b11 %
1"
#440
b11 $
0"
#445
b100 %
1"
#450
b100 $
0"
#455
0!
b0 %
1"
#460
1!
b0 $
0"
#465
b1 %
1"
#470
b1 $
0"
#475
b10 %
1"
#480
b10 $
0"
#485
b11 %
1"
#490
b11 $
0"
#495
b100 %
1"
#500
b100 $
0"
#505
0!
b0 %
1"
#510
1!
b0 $
0"
#515
b1 %
1"
#520
b1 $
0"
#525
b10 %
1"
#530
b10 $
0"
#535
b11 %
1"
#540
b11 $
0"
#545
b100 %
1"
#550
b100 $
0"
#555
0!
b0 %
1"
#560
1!
b0 $
0"
#565
b1 %
1"
#570
b1 $
0"
#575
b10 %
1"
#580
b10 $
0"
#585
b11 %
1"
#590
b11 $
0"
#595
b100 %
1"
#600
b100 $
0"
#605
0!
b0 %
1"
#610
1!
b0 $
0"
#615
b1 %
1"
#620
b1 $
0"
#625
b10 %
1"
#630
b10 $
0"
#635
b11 %
1"
#640
b11 $
0"
#645
b100 %
1"
#650
b100 $
0"
#655
0!
b0 %
1"
#660
1!
b0 $
0"
#665
b1 %
1"
#670
b1 $
0"
#675
b10 %
1"
#680
b10 $
0"
#685
b11 %
1"
#690
b11 $
0"
#695
b100 %
1"
#700
b100 $
0"
#705
0!
b0 %
1"
#710
1!
b0 $
0"
#715
b1 %
1"
#720
b1 $
0"
#725
b10 %
1"
#730
b10 $
0"
#735
b11 %
1"
#740
b11 $
0"
#745
b100 %
1"
#750
b100 $
0"
#755
0!
b0 %
1"
#760
1!
b0 $
0"
#765
b1 %
1"
#770
b1 $
0"
#775
b10 %
1"
#780
b10 $
0"
#785
b11 %
1"
#790
b11 $
0"
#795
b100 %
1"
#800
b100 $
0"
#805
0!
b0 %
1"
#810
1!
b0 $
0"
#815
b1 %
1"
#820
b1 $
0"
#825
b10 %
1"
#830
b10 $
0"
#835
b11 %
1"
#840
b11 $
0"
#845
b100 %
1"
#850
b100 $
0"
#855
0!
b0 %
1"
#860
1!
b0 $
0"
#865
b1 %
1"
#870
b1 $
0"
#875
b10 %
1"
#880
b10 $
0"
#885
b11 %
1"
#890
b11 $
0"
#895
b100 %
1"
#900
b100 $
0"
#905
0!
b0 %
1"
#910
1!
b0 $
0"
#915
b1 %
1"
#920
b1 $
0"
#925
b10 %
1"
#930
b10 $
0"
#935
b11 %
1"
#940
b11 $
0"
#945
b100 %
1"
#950
b100 $
0"
#955
0!
b0 %
1"
#960
1!
b0 $
0"
#965
b1 %
1"
#970
b1 $
0"
#975
b10 %
1"
#980
b10 $
0"
#985
b11 %
1"
#990
b11 $
0"
#995
b100 %
1"
#1000
b100 $
0"
#1005
0!
b0 %
1"
#1010
1!
b0 $
0"
#1015
b1 %
1"
